{
  "last_updated": "2025-12-10T16:05:07.204559+02:00",
  "current_rates": {
    "date": "2025-12-09",
    "rates": {
      "USD": {
        "buy": 23.12946428571429,
        "sell": 23.179464285714285,
        "mid": 23.154464285714287
      },
      "GBP": {
        "buy": 30.808446428571433,
        "sell": 30.87968232142857,
        "mid": 30.844064375000002
      },
      "EUR": {
        "buy": 26.90650580357143,
        "sell": 26.96930669642857,
        "mid": 26.93790625
      },
      "ZAR": {
        "buy": 1.3548662842950365,
        "sell": 1.357978117517285,
        "mid": 1.3564222009061608
      }
    }
  },
  "trends": {
    "USD": {
      "change": 0.048,
      "change_percent": -0.21,
      "direction": "down"
    },
    "GBP": {
      "change": 0.064,
      "change_percent": -0.21,
      "direction": "down"
    },
    "EUR": {
      "change": 0.02,
      "change_percent": -0.07,
      "direction": "down"
    },
    "ZAR": {
      "change": -0.006,
      "change_percent": 0.44,
      "direction": "up"
    }
  }
}
