{
  "last_updated": "2025-07-28T14:05:05.898341+02:00",
  "current_rates": {
    "date": "2025-07-25",
    "rates": {
      "USD": {
        "buy": 23.36238095238095,
        "sell": 23.412380952380953,
        "mid": 23.38738095238095
      },
      "GBP": {
        "buy": 31.38035009523809,
        "sell": 31.45453380952381,
        "mid": 31.417441952380948
      },
      "EUR": {
        "buy": 27.37370176190476,
        "sell": 27.436969238095237,
        "mid": 27.4053355
      },
      "ZAR": {
        "buy": 1.3134894977865768,
        "sell": 1.3163006185804376,
        "mid": 1.3148950581835073
      }
    }
  },
  "trends": {
    "USD": {
      "change": 0.064,
      "change_percent": -0.27,
      "direction": "down"
    },
    "GBP": {
      "change": -0.168,
      "change_percent": 0.53,
      "direction": "up"
    },
    "EUR": {
      "change": -0.014,
      "change_percent": 0.05,
      "direction": "up"
    },
    "ZAR": {
      "change": -0.009,
      "change_percent": 0.68,
      "direction": "up"
    }
  }
}
