{
  "last_updated": "2026-07-02T15:08:10.675732+02:00",
  "current_rates": {
    "date": "2026-07-01",
    "rates": {
      "USD": {
        "buy": 18.124404761904763,
        "sell": 18.174404761904757,
        "mid": 18.149404761904762
      },
      "GBP": {
        "buy": 24.04383535714286,
        "sell": 24.11561767857142,
        "mid": 24.07972651785714
      },
      "EUR": {
        "buy": 20.66182142857143,
        "sell": 20.72063886904761,
        "mid": 20.69123014880952
      },
      "ZAR": {
        "buy": 1.1068609164135161,
        "sell": 1.1106469623134452,
        "mid": 1.1087539393634807
      }
    }
  },
  "trends": {
    "USD": {
      "change": 0.067,
      "change_percent": -0.37,
      "direction": "down"
    },
    "GBP": {
      "change": 0.137,
      "change_percent": -0.57,
      "direction": "down"
    },
    "EUR": {
      "change": 0.053,
      "change_percent": -0.26,
      "direction": "down"
    },
    "ZAR": {
      "change": 0.004,
      "change_percent": -0.36,
      "direction": "down"
    }
  }
}
