{
  "last_updated": "2025-07-31T14:05:07.118838+02:00",
  "current_rates": {
    "date": "2025-07-30",
    "rates": {
      "USD": {
        "buy": 22.998809523809523,
        "sell": 23.048809523809524,
        "mid": 23.023809523809526
      },
      "GBP": {
        "buy": 30.586116785714285,
        "sell": 30.65722154761905,
        "mid": 30.621669166666667
      },
      "EUR": {
        "buy": 26.36813511904762,
        "sell": 26.43006988095238,
        "mid": 26.399102499999998
      },
      "ZAR": {
        "buy": 1.2814277807758903,
        "sell": 1.2842136375382789,
        "mid": 1.2828207091570847
      }
    }
  },
  "trends": {
    "USD": {
      "change": -0.062,
      "change_percent": 0.27,
      "direction": "up"
    },
    "GBP": {
      "change": -0.12,
      "change_percent": 0.39,
      "direction": "up"
    },
    "EUR": {
      "change": -0.22,
      "change_percent": 0.83,
      "direction": "up"
    },
    "ZAR": {
      "change": -0.002,
      "change_percent": 0.16,
      "direction": "up"
    }
  }
}
