{
  "last_updated": "2026-01-05T15:05:12.428494+02:00",
  "current_rates": {
    "date": "2026-01-02",
    "rates": {
      "USD": {
        "buy": 22.04440476190476,
        "sell": 22.09440476190476,
        "mid": 22.06940476190476
      },
      "GBP": {
        "buy": 29.63870220238095,
        "sell": 29.71918384523809,
        "mid": 29.67894302380952
      },
      "EUR": {
        "buy": 25.844860142857144,
        "sell": 25.907899023809524,
        "mid": 25.876379583333332
      },
      "ZAR": {
        "buy": 1.335182961158104,
        "sell": 1.3385761916590284,
        "mid": 1.3368795764085664
      }
    }
  },
  "trends": {
    "USD": {
      "change": -0.067,
      "change_percent": 0.3,
      "direction": "up"
    },
    "GBP": {
      "change": -0.139,
      "change_percent": 0.47,
      "direction": "up"
    },
    "EUR": {
      "change": -0.145,
      "change_percent": 0.56,
      "direction": "up"
    },
    "ZAR": {
      "change": 0.0,
      "change_percent": -0.0,
      "direction": "stable"
    }
  }
}
